odoo/addons/stock_valuation_layer_by_category/README.rst
odoo/addons/stock_valuation_layer_by_category/__init__.py
odoo/addons/stock_valuation_layer_by_category/__manifest__.py
odoo/addons/stock_valuation_layer_by_category/i18n/fr.po
odoo/addons/stock_valuation_layer_by_category/i18n/it.po
odoo/addons/stock_valuation_layer_by_category/i18n/stock_valuation_layer_by_category.pot
odoo/addons/stock_valuation_layer_by_category/models/__init__.py
odoo/addons/stock_valuation_layer_by_category/models/stock_valuation_layer.py
odoo/addons/stock_valuation_layer_by_category/readme/CONTRIBUTORS.rst
odoo/addons/stock_valuation_layer_by_category/readme/DESCRIPTION.rst
odoo/addons/stock_valuation_layer_by_category/static/description/icon.png
odoo/addons/stock_valuation_layer_by_category/static/description/index.html
odoo/addons/stock_valuation_layer_by_category/views/stock_valuation_layer.xml
odoo14_addon_stock_valuation_layer_by_category-14.0.1.0.1.dev8.dist-info/METADATA
odoo14_addon_stock_valuation_layer_by_category-14.0.1.0.1.dev8.dist-info/WHEEL
odoo14_addon_stock_valuation_layer_by_category-14.0.1.0.1.dev8.dist-info/top_level.txt
odoo14_addon_stock_valuation_layer_by_category-14.0.1.0.1.dev8.dist-info/RECORD
